atmst/__init__.py
atmst/all.py
atmst/cartool.py
atmst/util.py
atmst/blockstore/__init__.py
atmst/blockstore/car_file.py
atmst/mst/__init__.py
atmst/mst/diff.py
atmst/mst/node.py
atmst/mst/node_store.py
atmst/mst/node_walker.py
atmst/mst/node_wrangler.py
atmst/mst/proof.py
atmst-0.0.6.dist-info/LICENSE
atmst-0.0.6.dist-info/METADATA
atmst-0.0.6.dist-info/WHEEL
atmst-0.0.6.dist-info/entry_points.txt
atmst-0.0.6.dist-info/top_level.txt
atmst-0.0.6.dist-info/RECORD
