Metadata-Version: 2.1
Name: atmst
Version: 0.0.6
Summary: A Python library for wrangling atproto-flavoured Merkle Search Trees
Author-email: David Buchanan <d@vidbuchanan.co.uk>
Project-URL: Homepage, https://github.com/DavidBuchanan314/atmst
Project-URL: Issues, https://github.com/DavidBuchanan314/atmst/issues
Classifier: Programming Language :: Python :: 3
Classifier: License :: OSI Approved :: MIT License
Classifier: Operating System :: OS Independent
Requires-Python: >=3.9
License-File: LICENSE
Requires-Dist: cbrrr<2,>=1.0.0
Requires-Dist: more-itertools
Requires-Dist: lru-dict
Provides-Extra: docs
Requires-Dist: sphinx; extra == "docs"
Requires-Dist: sphinx-rtd-theme; extra == "docs"
Requires-Dist: sphinxcontrib-jquery; extra == "docs"
